unbreakable/__init__.py
unbreakable/client.py
unbreakable/decorator.py
unbreakablecode-2.0.1.dist-info/licenses/LICENSE
unbreakablecode-2.0.1.dist-info/METADATA
unbreakablecode-2.0.1.dist-info/WHEEL
unbreakablecode-2.0.1.dist-info/top_level.txt
unbreakablecode-2.0.1.dist-info/RECORD
