Metadata-Version: 2.4
Name: unbreakablecode
Version: 2.0.1
Summary: Your code can never crash again - Powered by 3.3M Stack Overflow solutions
Home-page: https://fixitapi.dev
Author: UnbreakableCode Developer
Author-email: support@fixitapi.dev
License: MIT
Project-URL: Bug Tracker, https://github.com/unbreakablecode/unbreakablecode/issues
Project-URL: API Dashboard, https://fixitapi.dev
Project-URL: Documentation, https://fixitapi.dev
Keywords: error-handling crash-prevention self-healing stackexchange debugging
Classifier: Development Status :: 4 - Beta
Classifier: Intended Audience :: Developers
Classifier: Topic :: Software Development :: Libraries :: Python Modules
Classifier: Topic :: Software Development :: Quality Assurance
Classifier: Programming Language :: Python :: 3
Classifier: Programming Language :: Python :: 3.7
Classifier: Programming Language :: Python :: 3.8
Classifier: Programming Language :: Python :: 3.9
Classifier: Programming Language :: Python :: 3.10
Classifier: Programming Language :: Python :: 3.11
Classifier: Operating System :: OS Independent
Requires-Python: >=3.7
License-File: LICENSE
Requires-Dist: requests>=2.25.0
Dynamic: author
Dynamic: author-email
Dynamic: classifier
Dynamic: description
Dynamic: description-content-type
Dynamic: home-page
Dynamic: keywords
Dynamic: license
Dynamic: license-file
Dynamic: project-url
Dynamic: requires-dist
Dynamic: requires-python
Dynamic: summary
